sql2mermaid_cli/__init__.py
sql2mermaid_cli/analyze.py
sql2mermaid_cli/dependencies.py
sql2mermaid_cli/file.py
sql2mermaid_cli/main.py
sql2mermaid_cli/mermaid.py
sql2mermaid_cli/tables.py
sql2mermaid_cli-1.0.1.dist-info/LICENSE.md
sql2mermaid_cli-1.0.1.dist-info/METADATA
sql2mermaid_cli-1.0.1.dist-info/WHEEL
sql2mermaid_cli-1.0.1.dist-info/entry_points.txt
sql2mermaid_cli-1.0.1.dist-info/RECORD
