Metadata-Version: 2.1
Name: sql2mermaid-cli
Version: 1.0.1
Summary: CLI tool for converting SQL table dependencies to mermaid.js format.
Home-page: https://github.com/sattosan/sql2mermaid-cli
License: MIT
Author: sattosan
Author-email: sato.yuya1211@gmail.com
Requires-Python: >=3.8.1,<4.0.0
Classifier: License :: OSI Approved :: MIT License
Classifier: Programming Language :: Python :: 3
Classifier: Programming Language :: Python :: 3.9
Classifier: Programming Language :: Python :: 3.10
Classifier: Programming Language :: Python :: 3.11
Requires-Dist: sqlparse (>=0.4.3,<0.5.0)
Requires-Dist: typer (>=0.7.0,<0.8.0)
Project-URL: Repository, https://github.com/sattosan/sql2mermaid-cli
